slack_click/__init__.py
slack_click/async_click.py
slack_click-2.0.1.dist-info/LICENSE
slack_click-2.0.1.dist-info/WHEEL
slack_click-2.0.1.dist-info/METADATA
slack_click-2.0.1.dist-info/RECORD
